Metadata-Version: 2.1
Name: transcribe-zh-en-p3
Version: 0.1
Summary: A package to process video and generate video from input language to target language.
Home-page: https://github.com/Abdulhamid97Mousa/transcribe_zh_en_p3
Author: Abdulhamid Mousa
Author-email: mousa.abdulhamid97@gmail.com
License: UNKNOWN
Platform: UNKNOWN
Classifier: Programming Language :: Python :: 3.8
Classifier: License :: OSI Approved :: MIT License
Classifier: Operating System :: OS Independent
Requires-Dist: torch==2.4.1
Requires-Dist: python-dotenv
Requires-Dist: requests==2.32.3
Requires-Dist: submitit==1.5.2
Requires-Dist: wheel==0.45.1
Requires-Dist: numpy==1.23.5
Requires-Dist: pysrt==1.1.2
Requires-Dist: pydub==0.25.1
